MANIFEST.in
README.md
setup.py
django_ajax_auth.egg-info/PKG-INFO
django_ajax_auth.egg-info/SOURCES.txt
django_ajax_auth.egg-info/dependency_links.txt
django_ajax_auth.egg-info/not-zip-safe
django_ajax_auth.egg-info/requires.txt
django_ajax_auth.egg-info/top_level.txt
xauth/__init__.py
xauth/admin.py
xauth/apps.py
xauth/login_ajax_urls.py
xauth/login_urls.py
xauth/models.py
xauth/password_ajax_urls.py
xauth/password_urls.py
xauth/tests.py
xauth/urls.py
xauth/views.py
xauth/migrations/__init__.py